[
  {
    "timestamp": "2025-05-20 14:20:12.829381",
    "duration": 0,
    "shear_rate_1_per_s": 250.0,
    "viscosity_Pa_s": 3.11,
    "wet_thickness_m": 0.0002,
    "dry_thickness_m": 0.00012,
    "defect_risk": false,
    "uniformity_std": 0.005
  },
  {
    "timestamp": "2025-05-20 14:20:17.829381",
    "duration": 5,
    "shear_rate_1_per_s": 250.0,
    "viscosity_Pa_s": 3.11,
    "wet_thickness_m": 0.0002,
    "dry_thickness_m": 0.00012,
    "defect_risk": false,
    "uniformity_std": 0.005
  },
  {
    "timestamp": "2025-05-20 14:20:22.829381",
    "duration": 10,
    "shear_rate_1_per_s": 250.0,
    "viscosity_Pa_s": 3.11,
    "wet_thickness_m": 0.0002,
    "dry_thickness_m": 0.00012,
    "defect_risk": false,
    "uniformity_std": 0.005
  },
  {
    "timestamp": "2025-05-20 14:20:27.829381",
    "duration": 15,
    "shear_rate_1_per_s": 250.0,
    "viscosity_Pa_s": 3.11,
    "wet_thickness_m": 0.0002,
    "dry_thickness_m": 0.00012,
    "defect_risk": false,
    "uniformity_std": 0.005
  },
  {
    "timestamp": "2025-05-20 14:20:32.829381",
    "duration": 20,
    "shear_rate_1_per_s": 250.0,
    "viscosity_Pa_s": 3.11,
    "wet_thickness_m": 0.0002,
    "dry_thickness_m": 0.00012,
    "defect_risk": false,
    "uniformity_std": 0.005
  },
  {
    "timestamp": "2025-05-20 14:20:37.829381",
    "duration": 25,
    "shear_rate_1_per_s": 250.0,
    "viscosity_Pa_s": 3.11,
    "wet_thickness_m": 0.0002,
    "dry_thickness_m": 0.00012,
    "defect_risk": false,
    "uniformity_std": 0.005
  },
  {
    "timestamp": "2025-05-20 14:20:42.829381",
    "duration": 30,
    "shear_rate_1_per_s": 250.0,
    "viscosity_Pa_s": 3.11,
    "wet_thickness_m": 0.0002,
    "dry_thickness_m": 0.00012,
    "defect_risk": false,
    "uniformity_std": 0.005
  },
  {
    "timestamp": "2025-05-20 14:20:47.829381",
    "duration": 35,
    "shear_rate_1_per_s": 250.0,
    "viscosity_Pa_s": 3.11,
    "wet_thickness_m": 0.0002,
    "dry_thickness_m": 0.00012,
    "defect_risk": false,
    "uniformity_std": 0.005
  },
  {
    "timestamp": "2025-05-20 14:20:52.829381",
    "duration": 40,
    "shear_rate_1_per_s": 250.0,
    "viscosity_Pa_s": 3.11,
    "wet_thickness_m": 0.0002,
    "dry_thickness_m": 0.00012,
    "defect_risk": false,
    "uniformity_std": 0.005
  },
  {
    "timestamp": "2025-05-20 14:20:57.829381",
    "duration": 45,
    "shear_rate_1_per_s": 250.0,
    "viscosity_Pa_s": 3.11,
    "wet_thickness_m": 0.0002,
    "dry_thickness_m": 0.00012,
    "defect_risk": false,
    "uniformity_std": 0.005
  },
  {
    "timestamp": "2025-05-20 14:21:02.829381",
    "duration": 50,
    "shear_rate_1_per_s": 250.0,
    "viscosity_Pa_s": 3.11,
    "wet_thickness_m": 0.0002,
    "dry_thickness_m": 0.00012,
    "defect_risk": false,
    "uniformity_std": 0.005
  },
  {
    "timestamp": "2025-05-20 14:21:07.829381",
    "duration": 55,
    "shear_rate_1_per_s": 250.0,
    "viscosity_Pa_s": 3.11,
    "wet_thickness_m": 0.0002,
    "dry_thickness_m": 0.00012,
    "defect_risk": false,
    "uniformity_std": 0.005
  },
  {
    "timestamp": "2025-05-20 14:21:12.829381",
    "duration": 60,
    "shear_rate_1_per_s": 250.0,
    "viscosity_Pa_s": 3.11,
    "wet_thickness_m": 0.0002,
    "dry_thickness_m": 0.00012,
    "defect_risk": false,
    "uniformity_std": 0.005
  },
  {
    "timestamp": "2025-05-20 14:21:17.829381",
    "duration": 65,
    "shear_rate_1_per_s": 250.0,
    "viscosity_Pa_s": 3.11,
    "wet_thickness_m": 0.0002,
    "dry_thickness_m": 0.00012,
    "defect_risk": false,
    "uniformity_std": 0.005
  },
  {
    "timestamp": "2025-05-20 14:21:22.829381",
    "duration": 70,
    "shear_rate_1_per_s": 250.0,
    "viscosity_Pa_s": 3.11,
    "wet_thickness_m": 0.0002,
    "dry_thickness_m": 0.00012,
    "defect_risk": false,
    "uniformity_std": 0.005
  },
  {
    "timestamp": "2025-05-20 14:21:27.829381",
    "duration": 75,
    "shear_rate_1_per_s": 250.0,
    "viscosity_Pa_s": 3.11,
    "wet_thickness_m": 0.0002,
    "dry_thickness_m": 0.00012,
    "defect_risk": false,
    "uniformity_std": 0.005
  },
  {
    "timestamp": "2025-05-20 14:21:32.829381",
    "duration": 80,
    "shear_rate_1_per_s": 250.0,
    "viscosity_Pa_s": 3.11,
    "wet_thickness_m": 0.0002,
    "dry_thickness_m": 0.00012,
    "defect_risk": false,
    "uniformity_std": 0.005
  },
  {
    "timestamp": "2025-05-20 14:21:37.829381",
    "duration": 85,
    "shear_rate_1_per_s": 250.0,
    "viscosity_Pa_s": 3.11,
    "wet_thickness_m": 0.0002,
    "dry_thickness_m": 0.00012,
    "defect_risk": false,
    "uniformity_std": 0.005
  },
  {
    "timestamp": "2025-05-20 14:21:42.829381",
    "duration": 90,
    "shear_rate_1_per_s": 250.0,
    "viscosity_Pa_s": 3.11,
    "wet_thickness_m": 0.0002,
    "dry_thickness_m": 0.00012,
    "defect_risk": false,
    "uniformity_std": 0.005
  },
  {
    "timestamp": "2025-05-20 14:21:47.829381",
    "duration": 95,
    "shear_rate_1_per_s": 250.0,
    "viscosity_Pa_s": 3.11,
    "wet_thickness_m": 0.0002,
    "dry_thickness_m": 0.00012,
    "defect_risk": false,
    "uniformity_std": 0.005
  },
  {
    "timestamp": "2025-05-20 14:21:52.829381",
    "duration": 100,
    "shear_rate_1_per_s": 250.0,
    "viscosity_Pa_s": 3.11,
    "wet_thickness_m": 0.0002,
    "dry_thickness_m": 0.00012,
    "defect_risk": false,
    "uniformity_std": 0.005
  }
]